README
setup.py
src/django_metaimage.egg-info/PKG-INFO
src/django_metaimage.egg-info/SOURCES.txt
src/django_metaimage.egg-info/dependency_links.txt
src/django_metaimage.egg-info/requires.txt
src/django_metaimage.egg-info/top_level.txt
src/metaimage/__init__.py
src/metaimage/admin.py
src/metaimage/forms.py
src/metaimage/models.py
src/metaimage/tests.py
src/metaimage/testsettings.py
src/metaimage/urls.py
src/metaimage/views.py
src/metaimage/templatetags/__init__.py
src/metaimage/templatetags/metaimage_tags.py
src/metaimage/utils/__init__.py
src/metaimage/utils/openanything.py