Metadata-Version: 1.0
Name: django-metaimage
Version: 0.3
Summary: Wrapper around django-photologue dealing w/ remote images.
Home-page: https://github.com/limist/django-metaimage
Author: Kai Wu
Author-email: k@limist.com
License: GPLv3
Platform: UNKNOWN
Classifier: Development Status :: 3 - Alpha
Classifier: Framework :: Django
Classifier: Intended Audience :: Developers
Classifier: License :: OSI Approved :: GNU General Public License (GPL)
Classifier: Operating System :: OS Independent
Classifier: Programming Language :: Python
Classifier: Topic :: Internet :: WWW/HTTP
